dragonnfruit/__init__.py
dragonnfruit/attributions.py
dragonnfruit/io.py
dragonnfruit/marginalize.py
dragonnfruit/models.py
dragonnfruit/preprocessing.py
dragonnfruit-0.3.1.data/scripts/dragonnfruit
dragonnfruit-0.3.1.dist-info/LICENSE
dragonnfruit-0.3.1.dist-info/METADATA
dragonnfruit-0.3.1.dist-info/WHEEL
dragonnfruit-0.3.1.dist-info/top_level.txt
dragonnfruit-0.3.1.dist-info/RECORD
