Metadata-Version: 2.1
Name: dragonnfruit
Version: 0.3.1
Summary: dragonnfruit is a method for analyzing scATAC-seq experiments.
Home-page: https://github.com/jmschrei/dragonnfruit
Author: Jacob Schreiber
Author-email: jmschreiber91@gmail.com
License: LICENSE.txt
License-File: LICENSE
Requires-Dist: numpy >=1.14.2
Requires-Dist: scipy >=1.0.0
Requires-Dist: pandas >=1.3.3
Requires-Dist: pyBigWig >=0.3.17
Requires-Dist: torch >=1.9.0
Requires-Dist: tables >=3.8.0
